{
  "name" : "Bizzare. Ca devrait pas mettre 2 lignes de dates: une avec l'année; une avec Week 34?",
  "modified" : "2019-08-30 11:27:39",
  "requires" : [ "graph.tcpos", "scheme.TRA_ART" ],
  "important" : false,
  "username" : "egirod",
  "document_id" : -734059671,
  "type" : "REPORT",
  "report" : {"properties":{"css":{"header":{"text-transform":"uppercase"}},"active_step":"s1002"},"steps":[{"alias":"s0","steps":[{"alias":"s1000","columns":[{"alias":"s1000_c1004","name":"Shop","grouping":"GROUP","expression":{"path":"source.s0_c3","type":"TEXT","resettable":false},"properties":{"width":200.0},"resettable":false,"pivot":{"dimensions":null,"hash":1561809597}},{"alias":"s1000_c1033","name":"Q1","grouping":"SUM","expression":{"path":"shared.if","parameters":[{"path":"shared.and","parameters":[{"path":"shared.is_equal","parameters":[{"path":"shared.year","parameters":[{"path":"source.s0_c0","type":"DATE","resettable":false}],"type":"INTEGER","resettable":false},{"type":"INTEGER","value":"2019"}],"type":"BOOLEAN","resettable":false},{"path":"shared.is_equal","parameters":[{"path":"shared.quarter","parameters":[{"path":"source.s0_c0","type":"DATE","resettable":false}],"type":"TEXT","resettable":false},{"type":"TEXT","value":"Q1"}],"type":"BOOLEAN","resettable":false}],"type":"BOOLEAN","resettable":false},{"path":"source.s0_c1","type":"DECIMAL","resettable":false},{"path":"system.null"}],"type":"DECIMAL","resettable":false},"properties":{"format":"0,0.00","format_unit":"CHF","format_pos":"prefix","format_dec_length":2,"format_mand_decimals":true,"format_type":"unit"},"comment":"Effective amount of line: Year=2019, Quarter=Q1","resettable":false,"pivot":{"dimensions":null,"hash":1578433995}},{"alias":"s1000_c1034","name":"Q2","grouping":"SUM","expression":{"path":"shared.if","parameters":[{"path":"shared.and","parameters":[{"path":"shared.is_equal","parameters":[{"path":"shared.year","parameters":[{"path":"source.s0_c0","type":"DATE","resettable":false}],"type":"INTEGER","resettable":false},{"type":"INTEGER","value":"2019"}],"type":"BOOLEAN","resettable":false},{"path":"shared.is_equal","parameters":[{"path":"shared.quarter","parameters":[{"path":"source.s0_c0","type":"DATE","resettable":false}],"type":"TEXT","resettable":false},{"type":"TEXT","value":"Q2"}],"type":"BOOLEAN","resettable":false}],"type":"BOOLEAN","resettable":false},{"path":"source.s0_c1","type":"DECIMAL","resettable":false},{"path":"system.null"}],"type":"DECIMAL","resettable":false},"properties":{"format":"0,0.00","format_unit":"CHF","format_pos":"prefix","format_dec_length":2,"format_mand_decimals":true,"format_type":"unit"},"comment":"Effective amount of line: Year=2019, Quarter=Q2","resettable":false,"pivot":{"dimensions":null,"hash":320901404}},{"alias":"s1000_c1035","name":"Q3","grouping":"SUM","expression":{"path":"shared.if","parameters":[{"path":"shared.and","parameters":[{"path":"shared.is_equal","parameters":[{"path":"shared.year","parameters":[{"path":"source.s0_c0","type":"DATE","resettable":false}],"type":"INTEGER","resettable":false},{"type":"INTEGER","value":"2019"}],"type":"BOOLEAN","resettable":false},{"path":"shared.is_equal","parameters":[{"path":"shared.quarter","parameters":[{"path":"source.s0_c0","type":"DATE","resettable":false}],"type":"TEXT","resettable":false},{"type":"TEXT","value":"Q3"}],"type":"BOOLEAN","resettable":false}],"type":"BOOLEAN","resettable":false},{"path":"source.s0_c1","type":"DECIMAL","resettable":false},{"path":"system.null"}],"type":"DECIMAL","resettable":false},"properties":{"format":"0,0.00","format_unit":"CHF","format_pos":"prefix","format_dec_length":2,"format_mand_decimals":true,"format_type":"unit"},"comment":"Effective amount of line: Year=2019, Quarter=Q3","resettable":false,"pivot":{"dimensions":null,"hash":-25770592}},{"alias":"s1000_c1036","name":"Q4","grouping":"SUM","expression":{"path":"shared.if","parameters":[{"path":"shared.and","parameters":[{"path":"shared.is_equal","parameters":[{"path":"shared.year","parameters":[{"path":"source.s0_c0","type":"DATE","resettable":false}],"type":"INTEGER","resettable":false},{"type":"INTEGER","value":"2019"}],"type":"BOOLEAN","resettable":false},{"path":"shared.is_equal","parameters":[{"path":"shared.quarter","parameters":[{"path":"source.s0_c0","type":"DATE","resettable":false}],"type":"TEXT","resettable":false},{"type":"TEXT","value":"Q4"}],"type":"BOOLEAN","resettable":false}],"type":"BOOLEAN","resettable":false},{"path":"source.s0_c1","type":"DECIMAL","resettable":false},{"path":"system.null"}],"type":"DECIMAL","resettable":false},"properties":{"format":"0,0.00","format_unit":"CHF","format_pos":"prefix","format_dec_length":2,"format_mand_decimals":true,"format_type":"unit"},"comment":"Effective amount of line: Year=2019, Quarter=Q4","resettable":false,"pivot":{"dimensions":null,"hash":2033716938}},{"alias":"s1000_c1029","name":"Q1","grouping":"SUM","expression":{"path":"shared.if","parameters":[{"path":"shared.and","parameters":[{"path":"shared.is_equal","parameters":[{"path":"shared.year","parameters":[{"path":"source.s0_c0","type":"DATE","resettable":false}],"type":"INTEGER","resettable":false},{"type":"INTEGER","value":"2018"}],"type":"BOOLEAN","resettable":false},{"path":"shared.is_equal","parameters":[{"path":"shared.quarter","parameters":[{"path":"source.s0_c0","type":"DATE","resettable":false}],"type":"TEXT","resettable":false},{"type":"TEXT","value":"Q1"}],"type":"BOOLEAN","resettable":false}],"type":"BOOLEAN","resettable":false},{"path":"source.s0_c1","type":"DECIMAL","resettable":false},{"path":"system.null"}],"type":"DECIMAL","resettable":false},"properties":{"format":"0,0.00","format_unit":"CHF","format_pos":"prefix","format_dec_length":2,"format_mand_decimals":true,"format_type":"unit"},"comment":"Effective amount of line: Year=2018, Quarter=Q1","resettable":false,"pivot":{"dimensions":null,"hash":-613547969}},{"alias":"s1000_c1030","name":"Q2","grouping":"SUM","expression":{"path":"shared.if","parameters":[{"path":"shared.and","parameters":[{"path":"shared.is_equal","parameters":[{"path":"shared.year","parameters":[{"path":"source.s0_c0","type":"DATE","resettable":false}],"type":"INTEGER","resettable":false},{"type":"INTEGER","value":"2018"}],"type":"BOOLEAN","resettable":false},{"path":"shared.is_equal","parameters":[{"path":"shared.quarter","parameters":[{"path":"source.s0_c0","type":"DATE","resettable":false}],"type":"TEXT","resettable":false},{"type":"TEXT","value":"Q2"}],"type":"BOOLEAN","resettable":false}],"type":"BOOLEAN","resettable":false},{"path":"source.s0_c1","type":"DECIMAL","resettable":false},{"path":"system.null"}],"type":"DECIMAL","resettable":false},"properties":{"format":"0,0.00","format_unit":"CHF","format_pos":"prefix","format_dec_length":2,"format_mand_decimals":true,"format_type":"unit"},"comment":"Effective amount of line: Year=2018, Quarter=Q2","resettable":false,"pivot":{"dimensions":null,"hash":1962970523}},{"alias":"s1000_c1031","name":"Q3","grouping":"SUM","expression":{"path":"shared.if","parameters":[{"path":"shared.and","parameters":[{"path":"shared.is_equal","parameters":[{"path":"shared.year","parameters":[{"path":"source.s0_c0","type":"DATE","resettable":false}],"type":"INTEGER","resettable":false},{"type":"INTEGER","value":"2018"}],"type":"BOOLEAN","resettable":false},{"path":"shared.is_equal","parameters":[{"path":"shared.quarter","parameters":[{"path":"source.s0_c0","type":"DATE","resettable":false}],"type":"TEXT","resettable":false},{"type":"TEXT","value":"Q3"}],"type":"BOOLEAN","resettable":false}],"type":"BOOLEAN","resettable":false},{"path":"source.s0_c1","type":"DECIMAL","resettable":false},{"path":"system.null"}],"type":"DECIMAL","resettable":false},"properties":{"format":"0,0.00","format_unit":"CHF","format_pos":"prefix","format_dec_length":2,"format_mand_decimals":true,"format_type":"unit"},"comment":"Effective amount of line: Year=2018, Quarter=Q3","resettable":false,"pivot":{"dimensions":null,"hash":-517054128}},{"alias":"s1000_c1032","name":"Q4","grouping":"SUM","expression":{"path":"shared.if","parameters":[{"path":"shared.and","parameters":[{"path":"shared.is_equal","parameters":[{"path":"shared.year","parameters":[{"path":"source.s0_c0","type":"DATE","resettable":false}],"type":"INTEGER","resettable":false},{"type":"INTEGER","value":"2018"}],"type":"BOOLEAN","resettable":false},{"path":"shared.is_equal","parameters":[{"path":"shared.quarter","parameters":[{"path":"source.s0_c0","type":"DATE","resettable":false}],"type":"TEXT","resettable":false},{"type":"TEXT","value":"Q4"}],"type":"BOOLEAN","resettable":false}],"type":"BOOLEAN","resettable":false},{"path":"source.s0_c1","type":"DECIMAL","resettable":false},{"path":"system.null"}],"type":"DECIMAL","resettable":false},"properties":{"format":"0,0.00","format_unit":"CHF","format_pos":"prefix","format_dec_length":2,"format_mand_decimals":true,"format_type":"unit"},"comment":"Effective amount of line: Year=2018, Quarter=Q4","resettable":false,"pivot":{"dimensions":null,"hash":-857488132}}],"orderings":[{"column":"s1000_c1004","order":"ASCENDING"}],"grouping":true,"pivot":{"rows":[{"alias":"dim_0","column":"s0_c3"}],"columns":[{"alias":"dim_1","column":"s0_c0","path":"shared.year","recent":2,"dynamic_columns":true},{"alias":"dim_2","column":"s0_c0","path":"shared.quarter","dynamic_columns":true}],"measures":[{"alias":"measure_0","grouping":"SUM","column":"s0_c1"}],"dynamic_columns":true},"name":"Effective amount of line","properties":{"sets":{"enabled":true,"items":[{"name":"2019","columns":["s1000_c1033","s1000_c1034","s1000_c1035","s1000_c1036"]},{"name":"2018","columns":["s1000_c1029","s1000_c1030","s1000_c1031","s1000_c1032"]}]},"grouping_collapsed":true}},{"alias":"s1001","columns":[{"alias":"s1001_c1002","name":"Shop","grouping":"GROUP","expression":{"path":"source.s0_c3","type":"TEXT","resettable":false},"properties":{"width":200.0},"resettable":false,"pivot":{"dimensions":null,"hash":1561809597}},{"alias":"s1001_c1004","name":"2019","grouping":"SUM","expression":{"path":"shared.if","parameters":[{"path":"shared.and","parameters":[{"path":"shared.is_equal","parameters":[{"path":"shared.year","parameters":[{"path":"source.s0_c0","type":"DATE","resettable":false}],"type":"INTEGER","resettable":false},{"type":"INTEGER","value":"2019"}],"type":"BOOLEAN","resettable":false},{"path":"shared.is_same_week","parameters":[{"path":"source.s0_c0","type":"DATE","resettable":false}],"type":"BOOLEAN","resettable":false}],"type":"BOOLEAN","resettable":false},{"path":"source.s0_c1","type":"DECIMAL","resettable":false},{"path":"system.null"}],"type":"DECIMAL","resettable":false},"properties":{"format":"0,0.00","format_unit":"CHF","format_pos":"prefix","format_dec_length":2,"format_mand_decimals":true,"format_type":"unit"},"comment":"Effective amount of line: Year=2019, Date=WEEK 34","resettable":false,"pivot":{"dimensions":null,"hash":594844850}},{"alias":"s1001_c1005","name":"2018","grouping":"SUM","expression":{"path":"shared.if","parameters":[{"path":"shared.and","parameters":[{"path":"shared.is_equal","parameters":[{"path":"shared.year","parameters":[{"path":"source.s0_c0","type":"DATE","resettable":false}],"type":"INTEGER","resettable":false},{"type":"INTEGER","value":"2018"}],"type":"BOOLEAN","resettable":false},{"path":"shared.is_same_week","parameters":[{"path":"source.s0_c0","type":"DATE","resettable":false}],"type":"BOOLEAN","resettable":false}],"type":"BOOLEAN","resettable":false},{"path":"source.s0_c1","type":"DECIMAL","resettable":false},{"path":"system.null"}],"type":"DECIMAL","resettable":false},"properties":{"format":"0,0.00","format_unit":"CHF","format_pos":"prefix","format_dec_length":2,"format_mand_decimals":true,"format_type":"unit"},"comment":"Effective amount of line: Year=2018, Date=WEEK 34","resettable":false,"pivot":{"dimensions":null,"hash":1432873422}}],"orderings":[{"column":"s1001_c1002","order":"ASCENDING"}],"grouping":true,"pivot":{"rows":[{"alias":"dim_0","column":"s0_c3"}],"columns":[{"alias":"dim_1","column":"s0_c0","path":"shared.year","recent":2,"dynamic_columns":true},{"alias":"dim_2","column":"s0_c0","dates":["shared.is_same_week"],"dynamic_column_names":true}],"measures":[{"alias":"measure_0","grouping":"SUM","column":"s0_c1"}],"dynamic_columns":true,"dynamic_column_names":true},"name":"Effective amount of line WEEK 34","properties":{"grouping_collapsed":true}},{"alias":"s1002","columns":[{"alias":"s1002_c1003","name":"Shop","grouping":"GROUP","expression":{"path":"source.s0_c3","type":"TEXT","resettable":false},"properties":{"width":200.0},"resettable":false,"pivot":{"dimensions":null,"hash":1561809597}},{"alias":"s1002_c1005","name":"WEEK 35 2019","grouping":"SUM","expression":{"path":"shared.if","parameters":[{"path":"shared.is_current_week","parameters":[{"path":"source.s0_c0","type":"DATE","resettable":false}],"type":"BOOLEAN","resettable":false},{"path":"source.s0_c1","type":"DECIMAL","resettable":false},{"path":"system.null"}],"type":"DECIMAL","resettable":false},"properties":{"format":"0,0.00","format_unit":"CHF","format_pos":"prefix","format_dec_length":2,"format_mand_decimals":true,"format_type":"unit"},"comment":"Effective amount of line: Date=WEEK 35 2019","resettable":false,"pivot":{"dimensions":null,"hash":-1612602049}},{"alias":"s1002_c1006","name":"WEEK 35 2018","grouping":"SUM","expression":{"path":"shared.if","parameters":[{"path":"shared.is_this_week_last_year","parameters":[{"path":"source.s0_c0","type":"DATE","resettable":false}],"type":"BOOLEAN","resettable":false},{"path":"source.s0_c1","type":"DECIMAL","resettable":false},{"path":"system.null"}],"type":"DECIMAL","resettable":false},"properties":{"format":"0,0.00","format_unit":"CHF","format_pos":"prefix","format_dec_length":2,"format_mand_decimals":true,"format_type":"unit"},"comment":"Effective amount of line: Date=WEEK 35 2018","resettable":false,"pivot":{"dimensions":null,"hash":-402748880}},{"alias":"s1002_c1008","name":"30-08-2019","grouping":"SUM","expression":{"path":"shared.if","parameters":[{"path":"shared.is_today","parameters":[{"path":"source.s0_c0","type":"DATE","resettable":false}],"type":"BOOLEAN","resettable":false},{"path":"source.s0_c1","type":"DECIMAL","resettable":false},{"path":"system.null"}],"type":"DECIMAL","resettable":false},"properties":{"format":"0,0.00","format_unit":"CHF","format_pos":"prefix","format_dec_length":2,"format_mand_decimals":true,"format_type":"unit"},"comment":"Effective amount of line: Date=30-08-2019","resettable":false,"pivot":{"dimensions":null,"hash":1569180674}},{"alias":"s1002_c1010","name":"29-08-2019","grouping":"SUM","expression":{"path":"shared.if","parameters":[{"path":"shared.is_yesterday","parameters":[{"path":"source.s0_c0","type":"DATE","resettable":false}],"type":"BOOLEAN","resettable":false},{"path":"source.s0_c1","type":"DECIMAL","resettable":false},{"path":"system.null"}],"type":"DECIMAL","resettable":false},"properties":{"format":"0,0.00","format_unit":"CHF","format_pos":"prefix","format_dec_length":2,"format_mand_decimals":true,"format_type":"unit"},"comment":"Effective amount of line: Date=29-08-2019","resettable":false,"pivot":{"dimensions":null,"hash":-534200219}},{"alias":"s1002_c1012","name":"31-08-2018","grouping":"SUM","expression":{"path":"shared.if","parameters":[{"path":"shared.is_same_day_last_year","parameters":[{"path":"source.s0_c0","type":"DATE","resettable":false}],"type":"BOOLEAN","resettable":false},{"path":"source.s0_c1","type":"DECIMAL","resettable":false},{"path":"system.null"}],"type":"DECIMAL","resettable":false},"properties":{"format":"0,0.00","format_unit":"CHF","format_pos":"prefix","format_dec_length":2,"format_mand_decimals":true,"format_type":"unit"},"comment":"Effective amount of line: Date=31-08-2018","resettable":false,"pivot":{"dimensions":null,"hash":1284447236}},{"alias":"s1002_c1013","name":"30-08-2018","grouping":"SUM","expression":{"path":"shared.if","parameters":[{"path":"shared.is_yesterday_day_last_year","parameters":[{"path":"source.s0_c0","type":"DATE","resettable":false}],"type":"BOOLEAN","resettable":false},{"path":"source.s0_c1","type":"DECIMAL","resettable":false},{"path":"system.null"}],"type":"DECIMAL","resettable":false},"properties":{"format":"0,0.00","format_unit":"CHF","format_pos":"prefix","format_dec_length":2,"format_mand_decimals":true,"format_type":"unit"},"comment":"Effective amount of line: Date=30-08-2018","resettable":false,"pivot":{"dimensions":null,"hash":-2088952779}}],"orderings":[{"column":"s1002_c1003","order":"ASCENDING"}],"grouping":true,"pivot":{"rows":[{"alias":"dim_0","column":"s0_c3"}],"columns":[{"alias":"dim_1","column":"s0_c0","dates":["shared.is_current_week","shared.is_this_week_last_year","shared.is_today","shared.is_yesterday","shared.is_same_day_last_year","shared.is_yesterday_day_last_year"],"dynamic_column_names":true}],"measures":[{"alias":"measure_0","grouping":"SUM","column":"s0_c1"}],"dynamic_columns":true,"dynamic_column_names":true},"name":"Effective amount of line","properties":{"grouping_collapsed":true,"freezed_columns":["s1002_c1003"],"chart":{"type":"column_chart"}},"chart":true},{"alias":"s1003","columns":[{"alias":"s1003_c1006","name":"Shop","grouping":"GROUP","expression":{"path":"source.s0_c3","type":"TEXT","resettable":false},"properties":{"width":200.0},"resettable":false,"pivot":{"dimensions":null,"hash":1561809597}},{"alias":"s1003_c1007","name":"2014","grouping":"SUM","expression":{"path":"shared.if","parameters":[{"path":"shared.and","parameters":[{"path":"shared.is_equal","parameters":[{"path":"shared.year","parameters":[{"path":"source.s0_c0","type":"DATE","resettable":false}],"type":"INTEGER","resettable":false},{"type":"INTEGER","value":"2014"}],"type":"BOOLEAN","resettable":false},{"path":"shared.is_same_day_as_yesterday","parameters":[{"path":"source.s0_c0","type":"DATE","resettable":false}],"type":"BOOLEAN","resettable":false}],"type":"BOOLEAN","resettable":false},{"path":"source.s0_c1","type":"DECIMAL","resettable":false},{"path":"system.null"}],"type":"DECIMAL","resettable":false},"properties":{"format":"0,0.00","format_unit":"CHF","format_pos":"prefix","format_dec_length":2,"format_mand_decimals":true,"format_type":"unit"},"comment":"Effective amount of line: Year=2014, Date=W35 D3","resettable":false,"pivot":{"dimensions":null,"hash":885920556}},{"alias":"s1003_c1014","name":"2015","grouping":"SUM","expression":{"path":"shared.if","parameters":[{"path":"shared.and","parameters":[{"path":"shared.is_equal","parameters":[{"path":"shared.year","parameters":[{"path":"source.s0_c0","type":"DATE","resettable":false}],"type":"INTEGER","resettable":false},{"type":"INTEGER","value":"2015"}],"type":"BOOLEAN","resettable":false},{"path":"shared.is_same_day_as_yesterday","parameters":[{"path":"source.s0_c0","type":"DATE","resettable":false}],"type":"BOOLEAN","resettable":false}],"type":"BOOLEAN","resettable":false},{"path":"source.s0_c1","type":"DECIMAL","resettable":false},{"path":"system.null"}],"type":"DECIMAL","resettable":false},"properties":{"format":"0,0.00","format_unit":"CHF","format_pos":"prefix","format_dec_length":2,"format_mand_decimals":true,"format_type":"unit"},"comment":"Effective amount of line: Year=2015, Date=W35 D3","resettable":false,"pivot":{"dimensions":null,"hash":1795380221}},{"alias":"s1003_c1015","name":"2016","grouping":"SUM","expression":{"path":"shared.if","parameters":[{"path":"shared.and","parameters":[{"path":"shared.is_equal","parameters":[{"path":"shared.year","parameters":[{"path":"source.s0_c0","type":"DATE","resettable":false}],"type":"INTEGER","resettable":false},{"type":"INTEGER","value":"2016"}],"type":"BOOLEAN","resettable":false},{"path":"shared.is_same_day_as_yesterday","parameters":[{"path":"source.s0_c0","type":"DATE","resettable":false}],"type":"BOOLEAN","resettable":false}],"type":"BOOLEAN","resettable":false},{"path":"source.s0_c1","type":"DECIMAL","resettable":false},{"path":"system.null"}],"type":"DECIMAL","resettable":false},"properties":{"format":"0,0.00","format_unit":"CHF","format_pos":"prefix","format_dec_length":2,"format_mand_decimals":true,"format_type":"unit"},"comment":"Effective amount of line: Year=2016, Date=W35 D3","resettable":false,"pivot":{"dimensions":null,"hash":-1318688041}},{"alias":"s1003_c1016","name":"2017","grouping":"SUM","expression":{"path":"shared.if","parameters":[{"path":"shared.and","parameters":[{"path":"shared.is_equal","parameters":[{"path":"shared.year","parameters":[{"path":"source.s0_c0","type":"DATE","resettable":false}],"type":"INTEGER","resettable":false},{"type":"INTEGER","value":"2017"}],"type":"BOOLEAN","resettable":false},{"path":"shared.is_same_day_as_yesterday","parameters":[{"path":"source.s0_c0","type":"DATE","resettable":false}],"type":"BOOLEAN","resettable":false}],"type":"BOOLEAN","resettable":false},{"path":"source.s0_c1","type":"DECIMAL","resettable":false},{"path":"system.null"}],"type":"DECIMAL","resettable":false},"properties":{"format":"0,0.00","format_unit":"CHF","format_pos":"prefix","format_dec_length":2,"format_mand_decimals":true,"format_type":"unit"},"comment":"Effective amount of line: Year=2017, Date=W35 D3","resettable":false,"pivot":{"dimensions":null,"hash":1005559071}},{"alias":"s1003_c1017","name":"2018","grouping":"SUM","expression":{"path":"shared.if","parameters":[{"path":"shared.and","parameters":[{"path":"shared.is_equal","parameters":[{"path":"shared.year","parameters":[{"path":"source.s0_c0","type":"DATE","resettable":false}],"type":"INTEGER","resettable":false},{"type":"INTEGER","value":"2018"}],"type":"BOOLEAN","resettable":false},{"path":"shared.is_same_day_as_yesterday","parameters":[{"path":"source.s0_c0","type":"DATE","resettable":false}],"type":"BOOLEAN","resettable":false}],"type":"BOOLEAN","resettable":false},{"path":"source.s0_c1","type":"DECIMAL","resettable":false},{"path":"system.null"}],"type":"DECIMAL","resettable":false},"properties":{"format":"0,0.00","format_unit":"CHF","format_pos":"prefix","format_dec_length":2,"format_mand_decimals":true,"format_type":"unit"},"comment":"Effective amount of line: Year=2018, Date=W35 D3","resettable":false,"pivot":{"dimensions":null,"hash":-1158106983}},{"alias":"s1003_c1018","name":"2019","grouping":"SUM","expression":{"path":"shared.if","parameters":[{"path":"shared.and","parameters":[{"path":"shared.is_equal","parameters":[{"path":"shared.year","parameters":[{"path":"source.s0_c0","type":"DATE","resettable":false}],"type":"INTEGER","resettable":false},{"type":"INTEGER","value":"2019"}],"type":"BOOLEAN","resettable":false},{"path":"shared.is_same_day_as_yesterday","parameters":[{"path":"source.s0_c0","type":"DATE","resettable":false}],"type":"BOOLEAN","resettable":false}],"type":"BOOLEAN","resettable":false},{"path":"source.s0_c1","type":"DECIMAL","resettable":false},{"path":"system.null"}],"type":"DECIMAL","resettable":false},"properties":{"format":"0,0.00","format_unit":"CHF","format_pos":"prefix","format_dec_length":2,"format_mand_decimals":true,"format_type":"unit"},"comment":"Effective amount of line: Year=2019, Date=W35 D3","resettable":false,"pivot":{"dimensions":null,"hash":-1198043741}}],"orderings":[{"column":"s1003_c1006","order":"ASCENDING"}],"grouping":true,"pivot":{"rows":[{"alias":"dim_0","column":"s0_c3"}],"columns":[{"alias":"dim_1","column":"s0_c0","path":"shared.year","dynamic_columns":true},{"alias":"dim_2","column":"s0_c0","dates":["shared.is_same_day_as_yesterday"],"dynamic_column_names":true}],"measures":[{"alias":"measure_0","grouping":"SUM","column":"s0_c1"}],"dynamic_columns":true,"dynamic_column_names":true},"name":"Effective amount of line W35 D3","properties":{"grouping_collapsed":true,"freezed_columns":["s1003_c1006"]},"chart":true}],"columns":[{"alias":"s0_c0","name":"Date","expression":{"path":"tcpos.TRA.BOOKKEEPING_DATE","type":"DATE","resettable":false},"resettable":false},{"alias":"s0_c1","name":"Effective amount of line","expression":{"path":"tcpos.TRA_ART.AMOUNT","type":"DECIMAL","resettable":false},"properties":{"format":"0,0.00","format_unit":"CHF","format_pos":"prefix","format_dec_length":2,"format_mand_decimals":true,"format_type":"unit"},"resettable":false},{"alias":"s0_c2","name":"Article","expression":{"path":"tcpos.ART.DESCRIPTION","type":"TEXT","resettable":false},"properties":{"width":250.0},"resettable":false},{"alias":"s0_c3","name":"Shop","expression":{"path":"tcpos.SHO.DESCRIPTION","type":"TEXT","resettable":false},"properties":{"width":200.0},"resettable":false}],"grouping":false,"name":"Ticket lines","properties":{"scheme":"Ticket lines"},"chart":false,"scheme":"TRA_ART"}] },
  "company" : "tekoe_mcs",
  "translatable" : false,
  "folder_id" : 91257518
}